CHANGES.txt
LICENSE.txt
MANIFEST.in
README.md
README_pypi.txt
pylint-report.txt
setup.py
jsonmanager/__init__.py
jsonmanager/coercion_tools.py
jsonmanager/defaults.py
jsonmanager/dispatching.py
jsonmanager/exceptions.py
jsonmanager/management_tools.py
jsonmanager/process_tools.py
jsonmanager/render_tools.py
jsonmanager/rules.py
jsonmanager/schema_types.py
jsonmanager/util.py
jsonmanager.egg-info/PKG-INFO
jsonmanager.egg-info/SOURCES.txt
jsonmanager.egg-info/dependency_links.txt
jsonmanager.egg-info/top_level.txt
jsonmanager/validation_tools/__init__.py
jsonmanager/validation_tools/pkg.py
jsonmanager/validation_tools/rules_validation.py
jsonmanager/validation_tools/structure_validation.py