Metadata-Version: 1.0
Name: jsonmanager
Version: 0.2.2
Summary: Validation, coercion, and forms for JSON.
Home-page: https://github.com/jmatthias/jsonmanager
Author: Josh Matthias
Author-email: jmatthias4570@gmail.com
License: LICENSE.txt
Platform: UNKNOWN
